Workbook

Sheet Dashboard
B2: E-COMMERCE SALES DASHBOARD
B5: FILTERS
B6: Category | C6: All | E6: Payment Method | F6: All | H6: Status | I6: All | K6: Year | L6: All
B8: KEY METRICS
B9: TOTAL SALES | E9: TOTAL ORDERS | H9: AVG ORDER VALUE | K9: UNITS SOLD
B10: =SUM(Data!N2:N81) -> 148696.93 | E10: =SUM(Data!P2:P81) -> 80 | H10: =IF(SUM(Data!P2:P81)=0,0,SUM(Data!N2:N81)/SUM(Data!P2:P81)) -> 1858.7116 | K10: =SUM(Data!O2:O81) -> 248
B13: CHARTS (all update together when you change the filters above)

Sheet Data
A1: ID | B1: Customer_Name | C1: Order_ID | D1: Order_Date | E1: Product | F1: Category | G1: Quantity | H1: Price | I1: Payment_Method | J1: Status | K1: Total | L1: Year | M1: Quarter | N1: Filtered_Total | O1: Filtered_Qty | P1: Filtered_Count
A2: 100 | B2: Customer_100 | C2: ORD-41285 | D2: 45618 | E2: Blender | F2: Home | G2: 3 | H2: 38 | I2: Cash on Delivery | J2: Shipped | K2: 114 | L2: =YEAR(D2) -> 2024 | M2: =YEAR(D2)&"-Q"&ROUNDUP(MONTH(D2)/3,0) -> 2024-Q4 | N2: =IF(AND(OR(Dashboard!$C$6="All",F2=Dashboard!$C$6),OR(Dashboard!$F$6="All",I2=Dashboard!$F$6),OR(Dashboard!$I$6="All",J2=Dashboard!$I$6),OR(Dashboard!$L$6="All",L2=Dashboard!$L$6)),K2,0) -> 114 | O2: =IF(AND(OR(Dashboard!$C$6="All",F2=Dashboard!$C$6),OR(Dashboard!$F$6="All",I2=Dashboard!$F$6),OR(Dashboard!$I$6="All",J2=Dashboard!$I$6),OR(Dashboard!$L$6="All",L2=Dashboard!$L$6)),G2,0) -> 3 | P2: =IF(AND(OR(Dashboard!$C$6="All",F2=Dashboard!$C$6),OR(Dashboard!$F$6="All",I2=Dashboard!$F$6),OR(Dashboard!$I$6="All",J2=Dashboard!$I$6),OR(Dashboard!$L$6="All",L2=Dashboard!$L$6)),1,0) -> 1
A3: 102 | B3: Customer_102 | C3: ORD-84355 | D3: 45649 | E3: Tennis Racket | F3: Sports | G3: 1 | H3: 389.05 | I3: PayPal | J3: Delivered | K3: 389.05 | L3: =YEAR(D3) -> 2024 | M3: =YEAR(D3)&"-Q"&ROUNDUP(MONTH(D3)/3,0) -> 2024-Q4 | N3: =IF(AND(OR(Dashboard!$C$6="All",F3=Dashboard!$C$6),OR(Dashboard!$F$6="All",I3=Dashboard!$F$6),OR(Dashboard!$I$6="All",J3=Dashboard!$I$6),OR(Dashboard!$L$6="All",L3=Dashboard!$L$6)),K3,0) -> 389.05 | O3: =IF(AND(OR(Dashboard!$C$6="All",F3=Dashboard!$C$6),OR(Dashboard!$F$6="All",I3=Dashboard!$F$6),OR(Dashboard!$I$6="All",J3=Dashboard!$I$6),OR(Dashboard!$L$6="All",L3=Dashboard!$L$6)),G3,0) -> 1 | P3: =IF(AND(OR(Dashboard!$C$6="All",F3=Dashboard!$C$6),OR(Dashboard!$F$6="All",I3=Dashboard!$F$6),OR(Dashboard!$I$6="All",J3=Dashboard!$I$6),OR(Dashboard!$L$6="All",L3=Dashboard!$L$6)),1,0) -> 1
A4: 103 | B4: Customer_103 | C4: ORD-57811 | D4: 45735 | E4: Science | F4: Books | G4: 5 | H4: 233.92 | I4: PayPal | J4: Processing | K4: 1169.6 | L4: =YEAR(D4) -> 2025 | M4: =YEAR(D4)&"-Q"&ROUNDUP(MONTH(D4)/3,0) -> 2025-Q1 | N4: =IF(AND(OR(Dashboard!$C$6="All",F4=Dashboard!$C$6),OR(Dashboard!$F$6="All",I4=Dashboard!$F$6),OR(Dashboard!$I$6="All",J4=Dashboard!$I$6),OR(Dashboard!$L$6="All",L4=Dashboard!$L$6)),K4,0) -> 1169.6 | O4: =IF(AND(OR(Dashboard!$C$6="All",F4=Dashboard!$C$6),OR(Dashboard!$F$6="All",I4=Dashboard!$F$6),OR(Dashboard!$I$6="All",J4=Dashboard!$I$6),OR(Dashboard!$L$6="All",L4=Dashboard!$L$6)),G4,0) -> 5 | P4: =IF(AND(OR(Dashboard!$C$6="All",F4=Dashboard!$C$6),OR(Dashboard!$F$6="All",I4=Dashboard!$F$6),OR(Dashboard!$I$6="All",J4=Dashboard!$I$6),OR(Dashboard!$L$6="All",L4=Dashboard!$L$6)),1,0) -> 1
A5: 104 | B5: Customer_104 | C5: ORD-93614 | D5: 45950 | E5: Biography | F5: Books | G5: 1 | H5: 552.51 | I5: Cash on Delivery | J5: Processing | K5: 552.51 | L5: =YEAR(D5) -> 2025 | M5: =YEAR(D5)&"-Q"&ROUNDUP(MONTH(D5)/3,0) -> 2025-Q4 | N5: =IF(AND(OR(Dashboard!$C$6="All",F5=Dashboard!$C$6),OR(Dashboard!$F$6="All",I5=Dashboard!$F$6),OR(Dashboard!$I$6="All",J5=Dashboard!$I$6),OR(Dashboard!$L$6="All",L5=Dashboard!$L$6)),K5,0) -> 552.51 | O5: =IF(AND(OR(Dashboard!$C$6="All",F5=Dashboard!$C$6),OR(Dashboard!$F$6="All",I5=Dashboard!$F$6),OR(Dashboard!$I$6="All",J5=Dashboard!$I$6),OR(Dashboard!$L$6="All",L5=Dashboard!$L$6)),G5,0) -> 1 | P5: =IF(AND(OR(Dashboard!$C$6="All",F5=Dashboard!$C$6),OR(Dashboard!$F$6="All",I5=Dashboard!$F$6),OR(Dashboard!$I$6="All",J5=Dashboard!$I$6),OR(Dashboard!$L$6="All",L5=Dashboard!$L$6)),1,0) -> 1
A6: 105 | B6: Customer_105 | C6: ORD-22442 | D6: 45616 | E6: Tennis Racket | F6: Sports | G6: 3 | H6: 122.06 | I6: Cash on Delivery | J6: Cancelled | K6: 366.18 | L6: =YEAR(D6) -> 2024 | M6: =YEAR(D6)&"-Q"&ROUNDUP(MONTH(D6)/3,0) -> 2024-Q4 | N6: =IF(AND(OR(Dashboard!$C$6="All",F6=Dashboard!$C$6),OR(Dashboard!$F$6="All",I6=Dashboard!$F$6),OR(Dashboard!$I$6="All",J6=Dashboard!$I$6),OR(Dashboard!$L$6="All",L6=Dashboard!$L$6)),K6,0) -> 366.18 | O6: =IF(AND(OR(Dashboard!$C$6="All",F6=Dashboard!$C$6),OR(Dashboard!$F$6="All",I6=Dashboard!$F$6),OR(Dashboard!$I$6="All",J6=Dashboard!$I$6),OR(Dashboard!$L$6="All",L6=Dashboard!$L$6)),G6,0) -> 3 | P6: =IF(AND(OR(Dashboard!$C$6="All",F6=Dashboard!$C$6),OR(Dashboard!$F$6="All",I6=Dashboard!$F$6),OR(Dashboard!$I$6="All",J6=Dashboard!$I$6),OR(Dashboard!$L$6="All",L6=Dashboard!$L$6)),1,0) -> 1
A7: 107 | B7: Customer_107 | C7: ORD-89122 | D7: 45660 | E7: Biography | F7: Books | G7: 5 | H7: 587.68 | I7: PayPal | J7: Returned | K7: 2938.4 | L7: =YEAR(D7) -> 2025 | M7: =YEAR(D7)&"-Q"&ROUNDUP(MONTH(D7)/3,0) -> 2025-Q1 | N7: =IF(AND(OR(Dashboard!$C$6="All",F7=Dashboard!$C$6),OR(Dashboard!$F$6="All",I7=Dashboard!$F$6),OR(Dashboard!$I$6="All",J7=Dashboard!$I$6),OR(Dashboard!$L$6="All",L7=Dashboard!$L$6)),K7,0) -> 2938.4 | O7: =IF(AND(OR(Dashboard!$C$6="All",F7=Dashboard!$C$6),OR(Dashboard!$F$6="All",I7=Dashboard!$F$6),OR(Dashboard!$I$6="All",J7=Dashboard!$I$6),OR(Dashboard!$L$6="All",L7=Dashboard!$L$6)),G7,0) -> 5 | P7: =IF(AND(OR(Dashboard!$C$6="All",F7=Dashboard!$C$6),OR(Dashboard!$F$6="All",I7=Dashboard!$F$6),OR(Dashboard!$I$6="All",J7=Dashboard!$I$6),OR(Dashboard!$L$6="All",L7=Dashboard!$L$6)),1,0) -> 1
A8: 108 | B8: Customer_108 | C8: ORD-64400 | D8: 45953 | E8: Science | F8: Books | G8: 1 | H8: 600.29 | I8: Cash on Delivery | J8: Processing | K8: 600.29 | L8: =YEAR(D8) -> 2025 | M8: =YEAR(D8)&"-Q"&ROUNDUP(MONTH(D8)/3,0) -> 2025-Q4 | N8: =IF(AND(OR(Dashboard!$C$6="All",F8=Dashboard!$C$6),OR(Dashboard!$F$6="All",I8=Dashboard!$F$6),OR(Dashboard!$I$6="All",J8=Dashboard!$I$6),OR(Dashboard!$L$6="All",L8=Dashboard!$L$6)),K8,0) -> 600.29 | O8: =IF(AND(OR(Dashboard!$C$6="All",F8=Dashboard!$C$6),OR(Dashboard!$F$6="All",I8=Dashboard!$F$6),OR(Dashboard!$I$6="All",J8=Dashboard!$I$6),OR(Dashboard!$L$6="All",L8=Dashboard!$L$6)),G8,0) -> 1 | P8: =IF(AND(OR(Dashboard!$C$6="All",F8=Dashboard!$C$6),OR(Dashboard!$F$6="All",I8=Dashboard!$F$6),OR(Dashboard!$I$6="All",J8=Dashboard!$I$6),OR(Dashboard!$L$6="All",L8=Dashboard!$L$6)),1,0) -> 1
A9: 109 | B9: Customer_109 | C9: ORD-18512 | D9: 45780 | E9: Tennis Racket | F9: Sports | G9: 5 | H9: 168.34 | I9: Credit Card | J9: Shipped | K9: 841.7 | L9: =YEAR(D9) -> 2025 | M9: =YEAR(D9)&"-Q"&ROUNDUP(MONTH(D9)/3,0) -> 2025-Q2 | N9: =IF(AND(OR(Dashboard!$C$6="All",F9=Dashboard!$C$6),OR(Dashboard!$F$6="All",I9=Dashboard!$F$6),OR(Dashboard!$I$6="All",J9=Dashboard!$I$6),OR(Dashboard!$L$6="All",L9=Dashboard!$L$6)),K9,0) -> 841.7 | O9: =IF(AND(OR(Dashboard!$C$6="All",F9=Dashboard!$C$6),OR(Dashboard!$F$6="All",I9=Dashboard!$F$6),OR(Dashboard!$I$6="All",J9=Dashboard!$I$6),OR(Dashboard!$L$6="All",L9=Dashboard!$L$6)),G9,0) -> 5 | P9: =IF(AND(OR(Dashboard!$C$6="All",F9=Dashboard!$C$6),OR(Dashboard!$F$6="All",I9=Dashboard!$F$6),OR(Dashboard!$I$6="All",J9=Dashboard!$I$6),OR(Dashboard!$L$6="All",L9=Dashboard!$L$6)),1,0) -> 1
A10: 110 | B10: Customer_110 | C10: ORD-61020 | D10: 45926 | E10: Basketball | F10: Sports | G10: 5 | H10: 400 | I10: Cash on Delivery | J10: Cancelled | K10: 2000 | L10: =YEAR(D10) -> 2025 | M10: =YEAR(D10)&"-Q"&ROUNDUP(MONTH(D10)/3,0) -> 2025-Q3 | N10: =IF(AND(OR(Dashboard!$C$6="All",F10=Dashboard!$C$6),OR(Dashboard!$F$6="All",I10=Dashboard!$F$6),OR(Dashboard!$I$6="All",J10=Dashboard!$I$6),OR(Dashboard!$L$6="All",L10=Dashboard!$L$6)),K10,0) -> 2000 | O10: =IF(AND(OR(Dashboard!$C$6="All",F10=Dashboard!$C$6),OR(Dashboard!$F$6="All",I10=Dashboard!$F$6),OR(Dashboard!$I$6="All",J10=Dashboard!$I$6),OR(Dashboard!$L$6="All",L10=Dashboard!$L$6)),G10,0) -> 5 | P10: =IF(AND(OR(Dashboard!$C$6="All",F10=Dashboard!$C$6),OR(Dashboard!$F$6="All",I10=Dashboard!$F$6),OR(Dashboard!$I$6="All",J10=Dashboard!$I$6),OR(Dashboard!$L$6="All",L10=Dashboard!$L$6)),1,0) -> 1
A11: 111 | B11: Customer_111 | C11: ORD-72349 | D11: 45952 | E11: Comics | F11: Books | G11: 2 | H11: 865.77 | I11: Credit Card | J11: Returned | K11: 1731.54 | L11: =YEAR(D11) -> 2025 | M11: =YEAR(D11)&"-Q"&ROUNDUP(MONTH(D11)/3,0) -> 2025-Q4 | N11: =IF(AND(OR(Dashboard!$C$6="All",F11=Dashboard!$C$6),OR(Dashboard!$F$6="All",I11=Dashboard!$F$6),OR(Dashboard!$I$6="All",J11=Dashboard!$I$6),OR(Dashboard!$L$6="All",L11=Dashboard!$L$6)),K11,0) -> 1731.54 | O11: =IF(AND(OR(Dashboard!$C$6="All",F11=Dashboard!$C$6),OR(Dashboard!$F$6="All",I11=Dashboard!$F$6),OR(Dashboard!$I$6="All",J11=Dashboard!$I$6),OR(Dashboard!$L$6="All",L11=Dashboard!$L$6)),G11,0) -> 2 | P11: =IF(AND(OR(Dashboard!$C$6="All",F11=Dashboard!$C$6),OR(Dashboard!$F$6="All",I11=Dashboard!$F$6),OR(Dashboard!$I$6="All",J11=Dashboard!$I$6),OR(Dashboard!$L$6="All",L11=Dashboard!$L$6)),1,0) -> 1
A12: 112 | B12: Customer_112 | C12: ORD-80867 | D12: 45718 | E12: Shoes | F12: Clothing | G12: 4 | H12: 752.13 | I12: Bank Transfer | J12: Delivered | K12: 3008.52 | L12: =YEAR(D12) -> 2025 | M12: =YEAR(D12)&"-Q"&ROUNDUP(MONTH(D12)/3,0) -> 2025-Q1 | N12: =IF(AND(OR(Dashboard!$C$6="All",F12=Dashboard!$C$6),OR(Dashboard!$F$6="All",I12=Dashboard!$F$6),OR(Dashboard!$I$6="All",J12=Dashboard!$I$6),OR(Dashboard!$L$6="All",L12=Dashboard!$L$6)),K12,0) -> 3008.52 | O12: =IF(AND(OR(Dashboard!$C$6="All",F12=Dashboard!$C$6),OR(Dashboard!$F$6="All",I12=Dashboard!$F$6),OR(Dashboard!$I$6="All",J12=Dashboard!$I$6),OR(Dashboard!$L$6="All",L12=Dashboard!$L$6)),G12,0) -> 4 | P12: =IF(AND(OR(Dashboard!$C$6="All",F12=Dashboard!$C$6),OR(Dashboard!$F$6="All",I12=Dashboard!$F$6),OR(Dashboard!$I$6="All",J12=Dashboard!$I$6),OR(Dashboard!$L$6="All",L12=Dashboard!$L$6)),1,0) -> 1
A13: 113 | B13: Customer_113 | C13: ORD-23994 | D13: 45862 | E13: Fiction | F13: Books | G13: 1 | H13: 411.81 | I13: Credit Card | J13: Processing | K13: 411.81 | L13: =YEAR(D13) -> 2025 | M13: =YEAR(D13)&"-Q"&ROUNDUP(MONTH(D13)/3,0) -> 2025-Q3 | N13: =IF(AND(OR(Dashboard!$C$6="All",F13=Dashboard!$C$6),OR(Dashboard!$F$6="All",I13=Dashboard!$F$6),OR(Dashboard!$I$6="All",J13=Dashboard!$I$6),OR(Dashboard!$L$6="All",L13=Dashboard!$L$6)),K13,0) -> 411.81 | O13: =IF(AND(OR(Dashboard!$C$6="All",F13=Dashboard!$C$6),OR(Dashboard!$F$6="All",I13=Dashboard!$F$6),OR(Dashboard!$I$6="All",J13=Dashboard!$I$6),OR(Dashboard!$L$6="All",L13=Dashboard!$L$6)),G13,0) -> 1 | P13: =IF(AND(OR(Dashboard!$C$6="All",F13=Dashboard!$C$6),OR(Dashboard!$F$6="All",I13=Dashboard!$F$6),OR(Dashboard!$I$6="All",J13=Dashboard!$I$6),OR(Dashboard!$L$6="All",L13=Dashboard!$L$6)),1,0) -> 1
... A81: 199 | B81: Customer_199 | C81: ORD-82922 | D81: 45679 | E81: Blender | F81: Home | G81: 5 | H81: 372.28 | I81: Credit Card | J81: Shipped | K81: 1861.4 | L81: =YEAR(D81) -> 2025 | M81: =YEAR(D81)&"-Q"&ROUNDUP(MONTH(D81)/3,0) -> 2025-Q1 | N81: =IF(AND(OR(Dashboard!$C$6="All",F81=Dashboard!$C$6),OR(Dashboard!$F$6="All",I81=Dashboard!$F$6),OR(Dashboard!$I$6="All",J81=Dashboard!$I$6),OR(Dashboard!$L$6="All",L81=Dashboard!$L$6)),K81,0) -> 1861.4 | O81: =IF(AND(OR(Dashboard!$C$6="All",F81=Dashboard!$C$6),OR(Dashboard!$F$6="All",I81=Dashboard!$F$6),OR(Dashboard!$I$6="All",J81=Dashboard!$I$6),OR(Dashboard!$L$6="All",L81=Dashboard!$L$6)),G81,0) -> 5 | P81: =IF(AND(OR(Dashboard!$C$6="All",F81=Dashboard!$C$6),OR(Dashboard!$F$6="All",I81=Dashboard!$F$6),OR(Dashboard!$I$6="All",J81=Dashboard!$I$6),OR(Dashboard!$L$6="All",L81=Dashboard!$L$6)),1,0) -> 1

Sheet Lists
A1: Category | B1: Payment | C1: Status | D1: Year | E1: Quarter
A2: All | B2: All | C2: All | D2: All | E2: All
A3: Books | B3: Bank Transfer | C3: Cancelled | D3: 2023 | E3: 2023-Q1
A4: Clothing | B4: Cash on Delivery | C4: Delivered | D4: 2024 | E4: 2023-Q2
A5: Electronics | B5: Credit Card | C5: Processing | D5: 2025 | E5: 2023-Q3
A6: Home | B6: PayPal | C6: Returned | E6: 2023-Q4
A7: Sports | C7: Shipped | E7: 2024-Q1
E8: 2024-Q2
E9: 2024-Q3
E10: 2024-Q4
E11: 2025-Q1
E12: 2025-Q2
E13: 2025-Q3
E14: 2025-Q4

Sheet PivotData
A1: Category | B1: Sales | C1: Qty | E1: Payment Method | F1: Sales | H1: Status | I1: Orders | J1: Sales | L1: Quarter | M1: Sales
A2: Books | B2: =SUMIF(Data!$F$2:$F$81,A2,Data!$N$2:$N$81) -> 38357.11 | C2: =SUMIF(Data!$F$2:$F$81,A2,Data!$O$2:$O$81) -> 69 | E2: Bank Transfer | F2: =SUMIF(Data!$I$2:$I$81,E2,Data!$N$2:$N$81) -> 41208.07 | H2: Cancelled | I2: =SUMIF(Data!$J$2:$J$81,H2,Data!$P$2:$P$81) -> 13 | J2: =SUMIF(Data!$J$2:$J$81,H2,Data!$N$2:$N$81) -> 26677.56 | L2: 2023-Q1 | M2: =SUMIF(Data!$M$2:$M$81,L2,Data!$N$2:$N$81) -> 705.78
A3: Clothing | B3: =SUMIF(Data!$F$2:$F$81,A3,Data!$N$2:$N$81) -> 26859.92 | C3: =SUMIF(Data!$F$2:$F$81,A3,Data!$O$2:$O$81) -> 42 | E3: Cash on Delivery | F3: =SUMIF(Data!$I$2:$I$81,E3,Data!$N$2:$N$81) -> 62071.54 | H3: Delivered | I3: =SUMIF(Data!$J$2:$J$81,H3,Data!$P$2:$P$81) -> 9 | J3: =SUMIF(Data!$J$2:$J$81,H3,Data!$N$2:$N$81) -> 12009.99 | L3: 2023-Q2 | M3: =SUMIF(Data!$M$2:$M$81,L3,Data!$N$2:$N$81) -> 1721.98
A4: Electronics | B4: =SUMIF(Data!$F$2:$F$81,A4,Data!$N$2:$N$81) -> 39313.94 | C4: =SUMIF(Data!$F$2:$F$81,A4,Data!$O$2:$O$81) -> 40 | E4: Credit Card | F4: =SUMIF(Data!$I$2:$I$81,E4,Data!$N$2:$N$81) -> 19990.3 | H4: Processing | I4: =SUMIF(Data!$J$2:$J$81,H4,Data!$P$2:$P$81) -> 17 | J4: =SUMIF(Data!$J$2:$J$81,H4,Data!$N$2:$N$81) -> 41849.56 | L4: 2023-Q3 | M4: =SUMIF(Data!$M$2:$M$81,L4,Data!$N$2:$N$81) -> 0
A5: Home | B5: =SUMIF(Data!$F$2:$F$81,A5,Data!$N$2:$N$81) -> 24429.71 | C5: =SUMIF(Data!$F$2:$F$81,A5,Data!$O$2:$O$81) -> 55 | E5: PayPal | F5: =SUMIF(Data!$I$2:$I$81,E5,Data!$N$2:$N$81) -> 25427.02 | H5: Returned | I5: =SUMIF(Data!$J$2:$J$81,H5,Data!$P$2:$P$81) -> 24 | J5: =SUMIF(Data!$J$2:$J$81,H5,Data!$N$2:$N$81) -> 38477.22 | L5: 2023-Q4 | M5: =SUMIF(Data!$M$2:$M$81,L5,Data!$N$2:$N$81) -> 0
A6: Sports | B6: =SUMIF(Data!$F$2:$F$81,A6,Data!$N$2:$N$81) -> 19736.25 | C6: =SUMIF(Data!$F$2:$F$81,A6,Data!$O$2:$O$81) -> 42 | H6: Shipped | I6: =SUMIF(Data!$J$2:$J$81,H6,Data!$P$2:$P$81) -> 17 | J6: =SUMIF(Data!$J$2:$J$81,H6,Data!$N$2:$N$81) -> 29682.6 | L6: 2024-Q1 | M6: =SUMIF(Data!$M$2:$M$81,L6,Data!$N$2:$N$81) -> 0
L7: 2024-Q2 | M7: =SUMIF(Data!$M$2:$M$81,L7,Data!$N$2:$N$81) -> 0
L8: 2024-Q3 | M8: =SUMIF(Data!$M$2:$M$81,L8,Data!$N$2:$N$81) -> 0
L9: 2024-Q4 | M9: =SUMIF(Data!$M$2:$M$81,L9,Data!$N$2:$N$81) -> 16368.48
L10: 2025-Q1 | M10: =SUMIF(Data!$M$2:$M$81,L10,Data!$N$2:$N$81) -> 55377.11
L11: 2025-Q2 | M11: =SUMIF(Data!$M$2:$M$81,L11,Data!$N$2:$N$81) -> 29339.03
L12: 2025-Q3 | M12: =SUMIF(Data!$M$2:$M$81,L12,Data!$N$2:$N$81) -> 24960.17
L13: 2025-Q4 | M13: =SUMIF(Data!$M$2:$M$81,L13,Data!$N$2:$N$81) -> 20224.38
